api/app/config.py
api/app/main.py
api/app/schemas.py
api/app/vision.py
api/app/routes/classification.py
api/tests/conftest.py
api/tests/routes/test_classification.py
holocron/__init__.py
holocron/version.py
holocron/models/__init__.py
holocron/models/presets.py
holocron/models/utils.py
holocron/models/classification/__init__.py
holocron/models/classification/darknet.py
holocron/models/classification/darknetv2.py
holocron/models/classification/darknetv3.py
holocron/models/classification/darknetv4.py
holocron/models/classification/pyconvresnet.py
holocron/models/classification/repvgg.py
holocron/models/classification/res2net.py
holocron/models/classification/resnet.py
holocron/models/classification/rexnet.py
holocron/models/classification/sknet.py
holocron/models/classification/tridentnet.py
holocron/models/detection/__init__.py
holocron/models/detection/yolo.py
holocron/models/detection/yolov2.py
holocron/models/detection/yolov4.py
holocron/models/segmentation/__init__.py
holocron/models/segmentation/unet.py
holocron/models/segmentation/unet3p.py
holocron/models/segmentation/unetpp.py
holocron/nn/__init__.py
holocron/nn/functional.py
holocron/nn/init.py
holocron/nn/modules/__init__.py
holocron/nn/modules/activation.py
holocron/nn/modules/attention.py
holocron/nn/modules/conv.py
holocron/nn/modules/downsample.py
holocron/nn/modules/dropblock.py
holocron/nn/modules/lambda_layer.py
holocron/nn/modules/loss.py
holocron/ops/__init__.py
holocron/ops/boxes.py
holocron/optim/__init__.py
holocron/optim/adabelief.py
holocron/optim/adamp.py
holocron/optim/functional.py
holocron/optim/lamb.py
holocron/optim/lars.py
holocron/optim/ralars.py
holocron/optim/tadam.py
holocron/optim/wrapper.py
holocron/trainer/__init__.py
holocron/trainer/classification.py
holocron/trainer/core.py
holocron/trainer/detection.py
holocron/trainer/segmentation.py
holocron/trainer/utils.py
holocron/utils/__init__.py
holocron/utils/misc.py
holocron/utils/data/__init__.py
holocron/utils/data/collate.py
pylocron-0.2.1.dist-info/LICENSE
pylocron-0.2.1.dist-info/METADATA
pylocron-0.2.1.dist-info/WHEEL
pylocron-0.2.1.dist-info/top_level.txt
pylocron-0.2.1.dist-info/zip-safe
pylocron-0.2.1.dist-info/RECORD
